evaluation_function_utils/__init__.py
evaluation_function_utils/client.py
evaluation_function_utils/errors.py
evaluation_function_utils-0.1.3.dist-info/WHEEL
evaluation_function_utils-0.1.3.dist-info/METADATA
evaluation_function_utils-0.1.3.dist-info/RECORD
