Metadata-Version: 2.1
Name: evaluation-function-utils
Version: 0.1.3
Summary: Miscellaneous Utilities to be used by LambdaFeedback Evaluation Functions
License: MIT
Author: RabidSheep55
Author-email: rabidsheep55@gmail.com
Requires-Python: >=3.7,<4.0
Classifier: License :: OSI Approved :: MIT License
Classifier: Programming Language :: Python :: 3
Classifier: Programming Language :: Python :: 3.10
Classifier: Programming Language :: Python :: 3.7
Classifier: Programming Language :: Python :: 3.8
Classifier: Programming Language :: Python :: 3.9
Requires-Dist: boto3 (>=1.24.38,<2.0.0)
Requires-Dist: python-dotenv (>=0.20.0,<0.21.0)
